{
    "title": "Kinshft",
	"art": {
		"background": "/assets/images/headers/Kinshift_NoLogo.jpg",
		"background_position": "50% 15%",
		"logo": "/assets/images/headers/Kinshift_Logo.png"
	},
	"page_data": {
		"headerBlock":
		{
			"company": "What If? Games",
			"title": "Generalist Programmer",
			"duration": "September 2024 - December 2024"
		},
		"projectBlocks": [

			{
				"projectVideo": "https://www.youtube.com/embed/Jt9BXTl1MKU?si=_ZBJwZmOwWLPDFPd"
			},
			{
				"blockTitle": "Summary",
				"description": [
					{
						"type": "text",
						"text": "Under Construction..."
					}
				]
			},  
			{
				"blockTitle": "Accomplishments",
				"list": [
					{
						"nav": "core-gameplay",
						"text": "Created Core Gameplay Systems"
					},
					{
						"nav": "arp-combat",
						"text": "Developed Near-Isometric ARPG Combat System"
					},
					{
						"nav": "inventory-and-equipment-systems",
						"text": "Created Inventory System & Equipment System"
					},
					{
						"nav": "modular-stat-and-modifier-system",
						"text": "Developed Scalable & Modular Stat / Modifier System"
					},
					{
						"nav": "scriptable-ai-system",
						"text": "Created Scriptable A.I System For Designers"
					},
					{
						"nav": "debug-framework",
						"text": "Created Debug Framework & System"
					},
					{
						"nav": "ui-tech",
						"text": "Main U.I Tech for Title"
					},
					{
						"nav": "cinematics-system",
						"text": "Developed Cinematics System"
					},
					{
						"nav": "split-screen-camera-system",
						"text": "Created Novel Split Screen Camera System"
					},
					{
						"nav": "p4-ownership",
						"text": "Setup, Administrated, and Owned Perforce Version Control"
					},
					{
						"nav": "managed-google-cloud-services",
						"text": "Managed Google Cloud Services"
					}
				]
			},        
			{
				"nav": "core-gameplay",
				"blockTitle": "Created Core Gameplay Systems",
				"description": [
					{
						"type": "text",
						"text": "Under Construction..."
					}
				]
			},        
			{
				"nav": "arp-combat",
				"blockTitle": "Developed Near-Isometric ARPG Combat System",
				"description": [
					{
						"type": "text",
						"text": "Under Construction..."
					}
				]
			},        
			{
				"nav": "inventory-and-equipment-systems",
				"blockTitle": "Created Inventory System & Equipment System",
				"description": [
					{
						"type": "text",
						"text": "Under Construction..."
					}
				]
			},        
			{
				"nav": "modular-stat-and-modifier-system",
				"blockTitle": "Developed Scalable & Modular Stat / Modifier System",
				"description": [
					{
						"type": "text",
						"text": "Under Construction..."
					}
				]
			},
			{
				"nav": "scriptable-ai-system",
				"blockTitle": "Created Scriptable A.I System For Designers",
				"description": [
					{
						"type": "text",
						"text": "Under Construction..."
					}
				]
			},   
			{
				"nav": "debug-framework",
				"blockTitle": "Created Debug Framework & System",
				"description": [
					{
						"type": "text",
						"text": "Under Construction..."
					}
				]
			},
			{
				"nav": "ui-tech",
				"blockTitle": "Main U.I Tech for Title",
				"description": [
					{
						"type": "text",
						"text": "Under Construction..."
					}
				]
			},          
			{
				"nav": "cinematics-system",
				"blockTitle": "Developed Cinematics System",
				"description": [
					{
						"type": "text",
						"text": "Under Construction..."
					}
				]
			},        
			{
				"nav": "split-screen-camera-system",
				"blockTitle": "Created Novel Split Screen Camera System",
				"description": [
					{
						"type": "text",
						"text": "Under Construction..."
					}
				]
			},        
			{
				"nav": "p4-ownership",
				"blockTitle": "Setup, Administrated, and Owned Perforce Version Control",
				"description": [
					{
						"type": "text",
						"text": "Under Construction..."
					}
				]
			},        
			{
				"nav": "managed-google-cloud-services",
				"blockTitle": "Managed Google Cloud Services",
				"description": [
					{
						"type": "text",
						"text": "Under Construction..."
					}
				]
			}
		]
	},
	"links": {
		"platforms": []
	}
}